ethopy_analysis/__init__.py
ethopy_analysis/_version.py
ethopy_analysis/cli.py
ethopy_analysis/config/__init__.py
ethopy_analysis/config/interactive.py
ethopy_analysis/config/settings.py
ethopy_analysis/config/styles.py
ethopy_analysis/data/__init__.py
ethopy_analysis/data/analysis.py
ethopy_analysis/data/loaders.py
ethopy_analysis/data/utils.py
ethopy_analysis/db/__init__.py
ethopy_analysis/db/schemas.py
ethopy_analysis/plots/__init__.py
ethopy_analysis/plots/animal.py
ethopy_analysis/plots/comparison.py
ethopy_analysis/plots/session.py
ethopy_analysis/plots/utils.py
ethopy_analysis-0.1.2.dist-info/METADATA
ethopy_analysis-0.1.2.dist-info/WHEEL
ethopy_analysis-0.1.2.dist-info/entry_points.txt
ethopy_analysis-0.1.2.dist-info/top_level.txt
ethopy_analysis-0.1.2.dist-info/RECORD
