Metadata-Version: 2.4
Name: ethopy-analysis
Version: 0.1.2
Summary: Data analysis and visualization package for Ethopy behavioral experiments
Author: Ethopy Analysis Contributors
License: MIT
Project-URL: Homepage, https://github.com/ef-lab/ethopy_analysis
Project-URL: Repository, https://github.com/ef-lab/ethopy_analysis
Project-URL: Documentation, https://ef-lab.github.io/ethopy_analysis
Project-URL: Bug Tracker, https://github.com/ef-lab/ethopy_analysis/issues
Keywords: neuroscience,behavior,data-analysis,visualization,ethopy
Classifier: Development Status :: 3 - Alpha
Classifier: Intended Audience :: Science/Research
Classifier: License :: OSI Approved :: MIT License
Classifier: Programming Language :: Python :: 3
Classifier: Programming Language :: Python :: 3.8
Classifier: Programming Language :: Python :: 3.9
Classifier: Programming Language :: Python :: 3.10
Classifier: Programming Language :: Python :: 3.11
Classifier: Topic :: Scientific/Engineering :: Bio-Informatics
Classifier: Topic :: Scientific/Engineering :: Visualization
Requires-Python: >=3.8
Requires-Dist: datajoint>=0.13.0
Requires-Dist: matplotlib>=3.5.0
Requires-Dist: networkx>=2.6.0
Requires-Dist: numpy>=1.20.0
Requires-Dist: pandas>=1.3.0
Requires-Dist: plotly>=5.0.0
Requires-Dist: seaborn>=0.11.0
Requires-Dist: click>=8.0.0
Requires-Dist: tqdm>=4.60.0
Requires-Dist: ipykernel>=6.0.0
Provides-Extra: dev
Requires-Dist: pytest>=7.0.0; extra == "dev"
Requires-Dist: pytest-cov>=4.0.0; extra == "dev"
Requires-Dist: black>=22.0.0; extra == "dev"
Requires-Dist: isort>=5.10.0; extra == "dev"
Requires-Dist: flake8>=4.0.0; extra == "dev"
Requires-Dist: mypy>=0.950; extra == "dev"
Requires-Dist: jupyter>=1.0.0; extra == "dev"
Requires-Dist: ipykernel>=6.0.0; extra == "dev"
Provides-Extra: docs
Requires-Dist: mkdocs>=1.4.0; extra == "docs"
Requires-Dist: mkdocs-material>=8.0.0; extra == "docs"
Requires-Dist: mkdocstrings[python]>=0.19.0; extra == "docs"
